ria_gui/__init__.py
ria_gui/_version.py
ria_gui/components.py
ria_gui/constants.py
ria_gui/gui.py
ria_gui/gui_components.py
ria_gui/io_utils.py
ria_gui/main.py
ria_gui/plot_window.py
ria_gui/processing.py
ria_gui/assets/app_256x256.ico
ria_gui/assets/app_ico.png
ria_gui/assets/ratiofish.ico
ria_gui/assets/figure/analysis.gif
ria_gui/assets/figure/live-plot.gif
ria_gui-1.7.10.2.dist-info/licenses/LICENSE
ria_gui-1.7.10.2.dist-info/METADATA
ria_gui-1.7.10.2.dist-info/WHEEL
ria_gui-1.7.10.2.dist-info/entry_points.txt
ria_gui-1.7.10.2.dist-info/top_level.txt
ria_gui-1.7.10.2.dist-info/RECORD
