Metadata-Version: 2.4
Name: ria-gui
Version: 1.7.10.2
Summary: RIA: Ratio Imaging Analyzer for biological quantification
Author: Kui Wang
Author-email: k@cns.ac.cn
Maintainer-email: Kui Wang <k@cns.ac.cn>
License: MIT License
Project-URL: Homepage, https://github.com/Epivitae/RatioImagingAnalyzer
Project-URL: Documentation, https://github.com/Epivitae/RatioImagingAnalyzer/wiki
Project-URL: Source, https://github.com/Epivitae/RatioImagingAnalyzer
Project-URL: Issues, https://github.com/Epivitae/RatioImagingAnalyzer/issues
Keywords: imaging,biology,quantification,ratio,gui,fluorescence
Classifier: Programming Language :: Python :: 3
Classifier: License :: OSI Approved :: MIT License
Classifier: Operating System :: OS Independent
Classifier: Topic :: Scientific/Engineering :: Image Processing
Classifier: Topic :: Scientific/Engineering :: Bio-Informatics
Requires-Python: >=3.8
License-File: LICENSE
Requires-Dist: numpy
Requires-Dist: matplotlib
Requires-Dist: tifffile
Requires-Dist: opencv-python
Requires-Dist: requests
Dynamic: license-file
